osint_python_test_bed_adapter-2.6.3.dist-info/licenses/LICENSE
test_bed_adapter/__init__.py
test_bed_adapter/kafka/__init__.py
test_bed_adapter/kafka/consumer_manager.py
test_bed_adapter/kafka/heartbeat_manager.py
test_bed_adapter/kafka/log_manager.py
test_bed_adapter/kafka/producer_manager.py
test_bed_adapter/options/__init__.py
test_bed_adapter/options/test_bed_options.py
test_bed_adapter/utils/__init__.py
test_bed_adapter/utils/helpers.py
test_bed_adapter/utils/key.py
osint_python_test_bed_adapter-2.6.3.dist-info/METADATA
osint_python_test_bed_adapter-2.6.3.dist-info/WHEEL
osint_python_test_bed_adapter-2.6.3.dist-info/top_level.txt
osint_python_test_bed_adapter-2.6.3.dist-info/RECORD
