Metadata-Version: 2.4
Name: osint-python-test-bed-adapter
Version: 2.6.3
Summary: Python adapter for Kafka
Home-page: https://github.com/OSINT-VDU-TNO/python-adapter
Author: TimovdK
Author-email: timo_kuil@hotmail.com
License: MIT
Classifier: Programming Language :: Python :: 3
Classifier: License :: OSI Approved :: MIT License
Classifier: Operating System :: OS Independent
License-File: LICENSE
Requires-Dist: confluent_kafka
Requires-Dist: fastavro
Requires-Dist: requests
Requires-Dist: authlib
Requires-Dist: cachetools
Requires-Dist: attrs
Requires-Dist: httpx
Dynamic: author
Dynamic: author-email
Dynamic: classifier
Dynamic: description
Dynamic: description-content-type
Dynamic: home-page
Dynamic: license
Dynamic: license-file
Dynamic: requires-dist
Dynamic: summary
